pysarpro-0.1.5.dist-info/METADATA
pysarpro-0.1.5.dist-info/WHEEL
pysarpro-0.1.5.dist-info/LICENSE.txt
pysarpro/_shared/transform.cp310-win_amd64.pyd
pysarpro/_shared/transform.cp310-win_amd64.lib
pysarpro/_shared/fast_exp.cp310-win_amd64.pyd
pysarpro/_shared/fast_exp.cp310-win_amd64.lib
pysarpro/_shared/geometry.cp310-win_amd64.pyd
pysarpro/_shared/geometry.cp310-win_amd64.lib
pysarpro/_shared/interpolation.cp310-win_amd64.pyd
pysarpro/_shared/interpolation.cp310-win_amd64.lib
pysarpro/io/_plugins/_colormixer.cp310-win_amd64.pyd
pysarpro/io/_plugins/_colormixer.cp310-win_amd64.lib
pysarpro/io/_plugins/_histograms.cp310-win_amd64.pyd
pysarpro/io/_plugins/_histograms.cp310-win_amd64.lib
pysarpro/util/_remap.cp310-win_amd64.pyd
pysarpro/util/_remap.cp310-win_amd64.lib
pysarpro/__init__.py
pysarpro/__init__.pyi
pysarpro/conftest.py
pysarpro/py.typed
pysarpro/_shared/__init__.py
pysarpro/_shared/_dependency_checks.py
pysarpro/_shared/_geometry.py
pysarpro/_shared/_tempfile.py
pysarpro/_shared/_warnings.py
pysarpro/_shared/coord.py
pysarpro/_shared/filters.py
pysarpro/_shared/tester.py
pysarpro/_shared/testing.py
pysarpro/_shared/utils.py
pysarpro/_shared/version_requirements.py
pysarpro/_shared/fast_exp.h
pysarpro/_shared/tests/__init__.py
pysarpro/_shared/tests/test_coord.py
pysarpro/_shared/tests/test_fast_exp.py
pysarpro/_shared/tests/test_geometry.py
pysarpro/_shared/tests/test_interpolation.py
pysarpro/_shared/tests/test_safe_as_int.py
pysarpro/_shared/tests/test_testing.py
pysarpro/_shared/tests/test_utils.py
pysarpro/_shared/tests/test_version_requirements.py
pysarpro/_shared/tests/test_warnings.py
pysarpro/data/__init__.py
pysarpro/data/__init__.pyi
pysarpro/data/_binary_blobs.py
pysarpro/data/_fetchers.py
pysarpro/data/_registry.py
pysarpro/data/README.txt
pysarpro/data/astronaut.png
pysarpro/data/tests/__init__.py
pysarpro/data/tests/test_data.py
pysarpro/data/01-sar/signal1_ac.npy
pysarpro/data/01-sar/signal1_rc.npy
pysarpro/data/01-sar/signal2_ac.npy
pysarpro/data/01-sar/signal2_rc.npy
pysarpro/io/__init__.py
pysarpro/io/_image_stack.py
pysarpro/io/_io.py
pysarpro-0.1.5.dist-info/RECORD
